{
  "cash": 0.0,
  "shares": 3.6828190172370174,
  "peak": 315.23,
  "trough": null,
  "last_price": 310.1400146484375,
  "last_action": "HOLD",
  "last_signal_reason": "No signal",
  "last_run_at": "2026-07-08T15:29:38.558163Z",
  "last_bar_at": "2026-07-08T14:30:00+00:00",
  "last_reopt_at": "2026-07-06T11:41:22.379002Z",
  "assets": {
    "ZSP.TO": {
      "cash": 1042.4974863808832,
      "shares": 0.0,
      "peak": null,
      "trough": 115.30999755859375,
      "last_price": 115.30999755859375,
      "last_action": "HOLD",
      "last_signal_reason": "No signal",
      "last_bar_at": "2026-07-08T14:30:00+00:00",
      "last_reopt_at": "2026-07-06T14:46:58.156384Z",
      "initial_cash": 1000.0
    },
    "AAPL.TO": {
      "cash": 0.0,
      "shares": 24.038462420187084,
      "peak": 41.599998474121094,
      "trough": null,
      "last_price": 41.599998474121094,
      "last_action": "HOLD",
      "last_signal_reason": "No signal",
      "last_bar_at": "2026-05-08T19:30:00+00:00",
      "last_reopt_at": "2026-05-09T03:23:36.628076Z",
      "initial_cash": 1000.0
    },
    "AAPL": {
      "cash": 0.0,
      "shares": 3.6828190172370174,
      "peak": 315.23,
      "trough": null,
      "last_price": 310.1400146484375,
      "last_action": "HOLD",
      "last_signal_reason": "No signal",
      "last_bar_at": "2026-07-08T14:30:00+00:00",
      "last_reopt_at": "2026-07-06T11:41:22.379002Z",
      "initial_cash": 1000.0
    },
    "AMD": {
      "cash": 1176.1238351917905,
      "shares": 0.0,
      "peak": null,
      "trough": 501.3999938964844,
      "last_price": 501.3999938964844,
      "last_action": "SELL",
      "last_signal_reason": "Price dropped from rolling peak threshold",
      "last_bar_at": "2026-07-08T14:30:00+00:00",
      "last_reopt_at": "2026-07-06T11:41:22.379002Z",
      "initial_cash": 1000.0
    },
    "GOOG": {
      "cash": 953.8076613653471,
      "shares": 0.0,
      "peak": null,
      "trough": 358.1000061035156,
      "last_price": 358.1000061035156,
      "last_action": "HOLD",
      "last_signal_reason": "No signal",
      "last_bar_at": "2026-07-08T14:30:00+00:00",
      "last_reopt_at": "2026-07-06T11:41:22.379002Z",
      "initial_cash": 1000.0
    },
    "MSFT": {
      "cash": 1053.7209612762088,
      "shares": 0.0,
      "peak": null,
      "trough": 382.1400146484375,
      "last_price": 382.1400146484375,
      "last_action": "HOLD",
      "last_signal_reason": "No signal",
      "last_bar_at": "2026-07-08T14:30:00+00:00",
      "last_reopt_at": "2026-07-06T11:41:22.379002Z",
      "initial_cash": 1000.0
    },
    "NVDA": {
      "cash": 912.0025936733651,
      "shares": 0.0,
      "peak": null,
      "trough": 191.2,
      "last_price": 196.61500549316406,
      "last_action": "HOLD",
      "last_signal_reason": "No signal",
      "last_bar_at": "2026-07-08T14:30:00+00:00",
      "last_reopt_at": "2026-07-06T11:41:22.379002Z",
      "initial_cash": 1000.0
    },
    "SMH": {
      "cash": 0.0,
      "shares": 1.9100565184352576,
      "peak": 578.1400146484375,
      "trough": null,
      "last_price": 578.1400146484375,
      "last_action": "HOLD",
      "last_signal_reason": "No signal",
      "last_bar_at": "2026-07-08T14:30:00+00:00",
      "last_reopt_at": "2026-07-06T11:41:22.379002Z",
      "initial_cash": 1000.0
    }
  },
  "portfolio_value": 7384.622185388531
}